s3transfer/__init__.py
s3transfer/compat.py
s3transfer/copies.py
s3transfer/delete.py
s3transfer/download.py
s3transfer/exceptions.py
s3transfer/futures.py
s3transfer/manager.py
s3transfer/subscribers.py
s3transfer/tasks.py
s3transfer/upload.py
s3transfer/utils.py
s3transfer_meiqia-0.1.10.dist-info/DESCRIPTION.rst
s3transfer_meiqia-0.1.10.dist-info/METADATA
s3transfer_meiqia-0.1.10.dist-info/RECORD
s3transfer_meiqia-0.1.10.dist-info/WHEEL
s3transfer_meiqia-0.1.10.dist-info/metadata.json
s3transfer_meiqia-0.1.10.dist-info/top_level.txt
